catalyst_pack_schemas/__init__.py
catalyst_pack_schemas/builder.py
catalyst_pack_schemas/cli.py
catalyst_pack_schemas/installer.py
catalyst_pack_schemas/models.py
catalyst_pack_schemas/utils.py
catalyst_pack_schemas/validators.py
catalyst_builder-1.1.0.dist-info/METADATA
catalyst_builder-1.1.0.dist-info/WHEEL
catalyst_builder-1.1.0.dist-info/entry_points.txt
catalyst_builder-1.1.0.dist-info/top_level.txt
catalyst_builder-1.1.0.dist-info/RECORD
